srai_voiceassist/__init__.py
srai_voiceassist/client_openai_audio.py
srai_voiceassist/client_perplexity.py
srai_voiceassist/script/__init__.py
srai_voiceassist/script/voiceassist.py
srai_voiceassist/service_playback.py
srai_voiceassist/service_prompt.py
srai_voiceassist/service_record.py
srai_voiceassist/service_transcribe.py
srai_voiceassist-0.1.1.dist-info/entry_points.txt
srai_voiceassist-0.1.1.dist-info/LICENSE
srai_voiceassist-0.1.1.dist-info/METADATA
srai_voiceassist-0.1.1.dist-info/WHEEL
srai_voiceassist-0.1.1.dist-info/RECORD
